web3_checksum/__init__.py
web3_checksum/get_checksum_address.py
eth_modules-0.1.1.dist-info/LICENSE.txt
eth_modules-0.1.1.dist-info/METADATA
eth_modules-0.1.1.dist-info/WHEEL
eth_modules-0.1.1.dist-info/top_level.txt
eth_modules-0.1.1.dist-info/RECORD
