Metadata-Version: 2.1
Name: eth-modules
Version: 0.1.1
Author: Air Compain
License: MIT
Keywords: eth-modules
License-File: LICENSE.txt
Requires-Dist: requests
Requires-Dist: web3
